heartbeat/__init__.py
heartbeat/heartbeat_observer.py
heartbeat/heatbeat_reporter.py
heartbeat/model/__init__.py
heartbeat/model/heartbeat_event.py
rosetta-dispatcher/__init__.py
rosetta-dispatcher/dispatch_client.py
rosetta-dispatcher/dispatch_server.py
rosetta_dispatcher/__init__.py
rosetta_dispatcher/aio_dispatch_client.py
rosetta_dispatcher/dispatch_client.py
rosetta_dispatcher/dispatch_server.py
rosetta_dispatcher/idtool.py
rosetta_dispatcher/redis_client.py
rosetta_dispatcher/singleton.py
rosetta_dispatcher/model/__init__.py
rosetta_dispatcher/model/dispatch_request_model.py
rosetta_dispatcher/model/dispatch_response_model.py
rosetta_dispatcher/model/dispatch_types.py
test/__init__.py
test/gen_response.py
test/http_async_client.py
test/test_aio_client.py
test/test_client.py
test/test_dispatcher.py
test/test_heartbeat_server.py
test/test_heatbeat_reporter.py
test/test_server.py
test/test_server_with_http_server.py
test/test_uuid.py
rosetta_dispatcher-0.0.27.dist-info/LICENSE
rosetta_dispatcher-0.0.27.dist-info/METADATA
rosetta_dispatcher-0.0.27.dist-info/WHEEL
rosetta_dispatcher-0.0.27.dist-info/top_level.txt
rosetta_dispatcher-0.0.27.dist-info/RECORD
