Metadata-Version: 2.1
Name: rosetta-dispatcher
Version: 0.0.27
Summary: batch worker client/server via redis queue.
Home-page: UNKNOWN
Author: Walker Wang
Author-email: walkerwk@foxmail.com
License: UNKNOWN
Platform: UNKNOWN
Classifier: Programming Language :: Python :: 3
Classifier: License :: OSI Approved :: MIT License
Classifier: Operating System :: OS Independent
Requires-Python: >=3.6
